spxl/__init__.py
spxl/container/__init__.py
spxl/container/dictionary.py
spxl/core/__init__.py
spxl/core/anonymousclass.py
spxl/core/asynceventhandler.py
spxl/core/baseclass.py
spxl/core/baseconstant.py
spxl/core/basemetaclass.py
spxl/core/basenode.py
spxl/core/builtins.py
spxl/core/enumflag.py
spxl/core/eventhandler.py
spxl/core/managedobject.py
spxl/core/weakedreference.py
spxl/dataformat/__init__.py
spxl/decorator/__init__.py
spxl/decorator/decorate_overridemethod.py
spxl/deprecated/__init__.py
spxl/deprecated/basenode.py
spxl/deprecated/decorator.py
spxl/deprecated/logger.py
spxl/ecs/__init__.py
spxl/ecs/component.py
spxl/ecs/entity.py
spxl/ecs/system.py
spxl/environment/__init__.py
spxl/environment/environment.py
spxl/environment/exitcodetype.py
spxl/environment/path.py
spxl/environment/platformtype.py
spxl/exception/__init__.py
spxl/exception/singletonerror.py
spxl/filesystem/__init__.py
spxl/filesystem/directory.py
spxl/filesystem/drive.py
spxl/filesystem/entry.py
spxl/filesystem/file.py
spxl/filesystem/stroage.py
spxl/future/__init__.py
spxl/future/baseagent.py
spxl/future/basebehaviour.py
spxl/future/eventhandler.py
spxl/future/eventnode.py
spxl/future/protocol.py
spxl/generic/__init__.py
spxl/http/__init__.py
spxl/http/httpstatuserror.py
spxl/manager/__init__.py
spxl/manager/baserepository.py
spxl/manager/sharedclass.py
spxl/manager/singleton.py
spxl/task/__init__.py
spxl/task/target.py
spxl/task/task.py
spxl/task/taskrunner.py
spxl/utility/__init__.py
spxl/utility/filefilter.py
spxl/utility/filter.py
spxl/utility/jsonutility.py
spxl/utility/logger.py
spxl/utility/loglevel.py
spxl/utility/stringutility.py
spxl-0.0.30.dist-info/LICENSE
spxl-0.0.30.dist-info/METADATA
spxl-0.0.30.dist-info/WHEEL
spxl-0.0.30.dist-info/top_level.txt
spxl-0.0.30.dist-info/RECORD
