Metadata-Version: 2.1
Name: spxl
Version: 0.0.30
Summary: A Sidoware Python Core Library
Home-page: https://sidoware.com
Author: sidoware
Author-email: developer@sidoware.com
Classifier: Programming Language :: Python :: 3
Classifier: License :: OSI Approved :: MIT License
Classifier: Operating System :: OS Independent
Requires-Python: >=3.7
License-File: LICENSE
